oarepo_rdm_records/__init__.py
oarepo_rdm_records/cli.py
oarepo_rdm_records/config.py
oarepo_rdm_records/ext.py
oarepo_rdm_records/metadata_extensions.py
oarepo_rdm_records/version.py
oarepo_rdm_records/included_mappings/v7/dataset-v1.0.0.json
oarepo_rdm_records/included_mappings/v7/dataset-v2.0.0.json
oarepo_rdm_records/jsonschemas/__init__.py
oarepo_rdm_records/jsonschemas/dataset-v1.0.0.json
oarepo_rdm_records/jsonschemas/dataset-v2.0.0.json
oarepo_rdm_records/jsonschemas/rdm-definitions-v1.0.0.json
oarepo_rdm_records/marshmallow/__init__.py
oarepo_rdm_records/marshmallow/access.py
oarepo_rdm_records/marshmallow/dataset.py
oarepo_rdm_records/marshmallow/dates.py
oarepo_rdm_records/marshmallow/identifier.py
oarepo_rdm_records/marshmallow/mixins.py
oarepo_rdm_records/marshmallow/person.py
oarepo_rdm_records/marshmallow/pids.py
oarepo_rdm_records/marshmallow/reference.py
oarepo_rdm_records/marshmallow/resource.py
oarepo_rdm_records/marshmallow/subject.py
oarepo_rdm_records/marshmallow/utils.py
oarepo_rdm_records-3.2.2.data/data/var/instance/taxonomies/contributorType.xlsx
oarepo_rdm_records-3.2.2.data/data/var/instance/taxonomies/languages.xlsx
oarepo_rdm_records-3.2.2.data/data/var/instance/taxonomies/licenses.xlsx
oarepo_rdm_records-3.2.2.data/data/var/instance/taxonomies/relationType.xlsx
oarepo_rdm_records-3.2.2.data/data/var/instance/taxonomies/resourceType.xlsx
tests/test_module/jsonschemas/__init__.py
tests/test_module/mappings/__init__.py
tests/test_module/mappings/v7/__init__.py
oarepo_rdm_records-3.2.2.dist-info/LICENSE
oarepo_rdm_records-3.2.2.dist-info/METADATA
oarepo_rdm_records-3.2.2.dist-info/WHEEL
oarepo_rdm_records-3.2.2.dist-info/entry_points.txt
oarepo_rdm_records-3.2.2.dist-info/top_level.txt
oarepo_rdm_records-3.2.2.dist-info/RECORD
