Metadata-Version: 2.1
Name: oarepo-rdm-records
Version: 3.2.2
Summary: OARepo rdm records data model
Home-page: https://github.com/oarepo/oarepo-rdm-records
Author: Alzbeta Pokorna
Author-email: alzbeta.pokorna@cesnet.cz
License: MIT
Platform: any
Classifier: Environment :: Web Environment
Classifier: Intended Audience :: Developers
Classifier: License :: OSI Approved :: MIT License
Classifier: Operating System :: OS Independent
Classifier: Programming Language :: Python
Classifier: Topic :: Internet :: WWW/HTTP :: Dynamic Content
Classifier: Topic :: Software Development :: Libraries :: Python Modules
Classifier: Programming Language :: Python :: 2
Classifier: Programming Language :: Python :: 2.7
Classifier: Programming Language :: Python :: 3
Classifier: Programming Language :: Python :: 3.5
Classifier: Development Status :: 4 - Beta
License-File: LICENSE
Requires-Dist: pycountry
Requires-Dist: oarepo-mapping-includes
Requires-Dist: oarepo-invenio-model
Requires-Dist: oarepo-validate
Requires-Dist: idutils
Requires-Dist: edtf
Requires-Dist: oarepo-multilingual
Requires-Dist: marshmallow-utils (>=0.4.0)
Requires-Dist: oarepo-taxonomies
Provides-Extra: tests
Requires-Dist: pydocstyle ; extra == 'tests'
Requires-Dist: oarepo[tests] (~=3.3.0) ; extra == 'tests'
